{
  "info": {
    "doesLoop": 0,
    "keyFrames": 21,
    "frameRate": 60
  },
  "skeleton": {
    "tracks": [
      {
        "name": "pm0071_51_00",
        "scale_type": "FixedVectorTrack",
        "scale": {
          "co": {
            "x": 1.0,
            "y": 1.0,
            "z": 1.0
          }
        },
        "rotate_type": "FixedRotationTrack",
        "rotate": {
          "co": {
            "x": 3,
            "y": 2,
            "z": 32769
          }
        },
        "translate_type": "FixedVectorTrack",
        "translate": {
          "co": {
            "x": 0.0,
            "y": 0.0,
            "z": 0.0
          }
        }
      },
      {
        "name": "origin",
        "scale_type": "FixedVectorTrack",
        "scale": {
          "co": {
            "x": 1.0,
            "y": 1.0,
            "z": 1.0
          }
        },
        "rotate_type": "FixedRotationTrack",
        "rotate": {
          "co": {
            "x": 3,
            "y": 2,
            "z": 32769
          }
        },
        "translate_type": "FixedVectorTrack",
        "translate": {
          "co": {
            "x": 0.0,
            "y": 0.0,
            "z": 0.0
          }
        }
      },
      {
        "name": "left_upper_eyelid_a",
        "scale_type": "FixedVectorTrack",
        "scale": {
          "co": {
            "x": 1.0,
            "y": 1.0,
            "z": 1.0
          }
        },
        "rotate_type": "DynamicRotationTrack",
        "rotate": {
          "co": [
            {
              "x": 5072,
              "y": 26230,
              "z": 24643
            },
            {
              "x": 3272,
              "y": 26570,
              "z": 25677
            },
            {
              "x": 64912,
              "y": 27269,
              "z": 27973
            },
            {
              "x": 61072,
              "y": 27933,
              "z": 30297
            },
            {
              "x": 59104,
              "y": 28401,
              "z": 31347
            },
            {
              "x": 58520,
              "y": 28737,
              "z": 31313
            },
            {
              "x": 57888,
              "y": 29029,
              "z": 31271
            },
            {
              "x": 57304,
              "y": 29261,
              "z": 31233
            },
            {
              "x": 56888,
              "y": 29413,
              "z": 31205
            },
            {
              "x": 56720,
              "y": 29465,
              "z": 31193
            },
            {
              "x": 56720,
              "y": 29465,
              "z": 31193
            },
            {
              "x": 56888,
              "y": 29413,
              "z": 31205
            },
            {
              "x": 57304,
              "y": 29261,
              "z": 31233
            },
            {
              "x": 57888,
              "y": 29029,
              "z": 31271
            },
            {
              "x": 58520,
              "y": 28737,
              "z": 31313
            },
            {
              "x": 59104,
              "y": 28401,
              "z": 31347
            },
            {
              "x": 61072,
              "y": 27933,
              "z": 30297
            },
            {
              "x": 64912,
              "y": 27269,
              "z": 27973
            },
            {
              "x": 3272,
              "y": 26570,
              "z": 25677
            },
            {
              "x": 5072,
              "y": 26230,
              "z": 24643
            },
            {
              "x": 5072,
              "y": 26230,
              "z": 24643
            }
          ]
        },
        "translate_type": "FixedVectorTrack",
        "translate": {
          "co": {
            "x": 14.499999999999998,
            "y": -3.9,
            "z": -1.5
          }
        }
      },
      {
        "name": "right_upper_eyelid_a",
        "scale_type": "FixedVectorTrack",
        "scale": {
          "co": {
            "x": 1.0,
            "y": 1.0,
            "z": 1.0
          }
        },
        "rotate_type": "DynamicRotationTrack",
        "rotate": {
          "co": [
            {
              "x": 60456,
              "y": 26229,
              "z": 40893
            },
            {
              "x": 62256,
              "y": 26569,
              "z": 39859
            },
            {
              "x": 616,
              "y": 27270,
              "z": 37563
            },
            {
              "x": 4456,
              "y": 27934,
              "z": 35239
            },
            {
              "x": 6424,
              "y": 28402,
              "z": 34189
            },
            {
              "x": 7008,
              "y": 28738,
              "z": 34223
            },
            {
              "x": 7640,
              "y": 29030,
              "z": 34265
            },
            {
              "x": 8224,
              "y": 29262,
              "z": 34303
            },
            {
              "x": 8640,
              "y": 29414,
              "z": 34331
            },
            {
              "x": 8808,
              "y": 29466,
              "z": 34343
            },
            {
              "x": 8808,
              "y": 29466,
              "z": 34343
            },
            {
              "x": 8640,
              "y": 29414,
              "z": 34331
            },
            {
              "x": 8224,
              "y": 29262,
              "z": 34303
            },
            {
              "x": 7640,
              "y": 29030,
              "z": 34265
            },
            {
              "x": 7008,
              "y": 28738,
              "z": 34223
            },
            {
              "x": 6424,
              "y": 28402,
              "z": 34189
            },
            {
              "x": 4456,
              "y": 27934,
              "z": 35239
            },
            {
              "x": 616,
              "y": 27270,
              "z": 37563
            },
            {
              "x": 62256,
              "y": 26569,
              "z": 39859
            },
            {
              "x": 60456,
              "y": 26229,
              "z": 40893
            },
            {
              "x": 60456,
              "y": 26229,
              "z": 40893
            }
          ]
        },
        "translate_type": "FixedVectorTrack",
        "translate": {
          "co": {
            "x": 14.499999999999998,
            "y": 3.9,
            "z": -1.5
          }
        }
      },
      {
        "name": "left_upper_eyelid_b",
        "scale_type": "FixedVectorTrack",
        "scale": {
          "co": {
            "x": 1.0,
            "y": 1.0,
            "z": 1.0
          }
        },
        "rotate_type": "DynamicRotationTrack",
        "rotate": {
          "co": [
            {
              "x": 50520,
              "y": 24149,
              "z": 22569
            },
            {
              "x": 49824,
              "y": 24421,
              "z": 22921
            },
            {
              "x": 48256,
              "y": 25041,
              "z": 23747
            },
            {
              "x": 46568,
              "y": 25721,
              "z": 24691
            },
            {
              "x": 45408,
              "y": 26177,
              "z": 25379
            },
            {
              "x": 44752,
              "y": 26385,
              "z": 25765
            },
            {
              "x": 44240,
              "y": 26497,
              "z": 26057
            },
            {
              "x": 43872,
              "y": 26541,
              "z": 26261
            },
            {
              "x": 43640,
              "y": 26549,
              "z": 26379
            },
            {
              "x": 43568,
              "y": 26549,
              "z": 26417
            },
            {
              "x": 43568,
              "y": 26549,
              "z": 26417
            },
            {
              "x": 43640,
              "y": 26549,
              "z": 26379
            },
            {
              "x": 43872,
              "y": 26541,
              "z": 26261
            },
            {
              "x": 44240,
              "y": 26497,
              "z": 26057
            },
            {
              "x": 44752,
              "y": 26385,
              "z": 25765
            },
            {
              "x": 45408,
              "y": 26177,
              "z": 25379
            },
            {
              "x": 46568,
              "y": 25721,
              "z": 24691
            },
            {
              "x": 48256,
              "y": 25041,
              "z": 23747
            },
            {
              "x": 49824,
              "y": 24421,
              "z": 22921
            },
            {
              "x": 50520,
              "y": 24149,
              "z": 22569
            },
            {
              "x": 50520,
              "y": 24149,
              "z": 22569
            }
          ]
        },
        "translate_type": "FixedVectorTrack",
        "translate": {
          "co": {
            "x": -1.7999999999999998,
            "y": 9.700000000000001,
            "z": -12.7
          }
        }
      },
      {
        "name": "right_upper_eyelid_b",
        "scale_type": "FixedVectorTrack",
        "scale": {
          "co": {
            "x": 1.0,
            "y": 1.0,
            "z": 1.0
          }
        },
        "rotate_type": "DynamicRotationTrack",
        "rotate": {
          "co": [
            {
              "x": 15008,
              "y": 24150,
              "z": 42967
            },
            {
              "x": 15704,
              "y": 24422,
              "z": 42615
            },
            {
              "x": 17272,
              "y": 25042,
              "z": 41789
            },
            {
              "x": 18960,
              "y": 25722,
              "z": 40845
            },
            {
              "x": 20120,
              "y": 26178,
              "z": 40157
            },
            {
              "x": 20776,
              "y": 26386,
              "z": 39771
            },
            {
              "x": 21288,
              "y": 26498,
              "z": 39479
            },
            {
              "x": 21656,
              "y": 26542,
              "z": 39275
            },
            {
              "x": 21888,
              "y": 26550,
              "z": 39157
            },
            {
              "x": 21960,
              "y": 26550,
              "z": 39119
            },
            {
              "x": 21960,
              "y": 26550,
              "z": 39119
            },
            {
              "x": 21888,
              "y": 26550,
              "z": 39157
            },
            {
              "x": 21656,
              "y": 26542,
              "z": 39275
            },
            {
              "x": 21288,
              "y": 26498,
              "z": 39479
            },
            {
              "x": 20776,
              "y": 26386,
              "z": 39771
            },
            {
              "x": 20120,
              "y": 26178,
              "z": 40157
            },
            {
              "x": 18960,
              "y": 25722,
              "z": 40845
            },
            {
              "x": 17272,
              "y": 25042,
              "z": 41789
            },
            {
              "x": 15704,
              "y": 24422,
              "z": 42615
            },
            {
              "x": 15008,
              "y": 24150,
              "z": 42967
            },
            {
              "x": 15008,
              "y": 24150,
              "z": 42967
            }
          ]
        },
        "translate_type": "FixedVectorTrack",
        "translate": {
          "co": {
            "x": -1.7999999999999998,
            "y": -9.700000000000001,
            "z": -12.7
          }
        }
      },
      {
        "name": "left_upper_eyelid_c",
        "scale_type": "FixedVectorTrack",
        "scale": {
          "co": {
            "x": 1.0,
            "y": 1.0,
            "z": 1.0
          }
        },
        "rotate_type": "DynamicRotationTrack",
        "rotate": {
          "co": [
            {
              "x": 37976,
              "y": 23017,
              "z": 31251
            },
            {
              "x": 37720,
              "y": 23501,
              "z": 31425
            },
            {
              "x": 37160,
              "y": 24669,
              "z": 31839
            },
            {
              "x": 36592,
              "y": 26113,
              "z": 32317
            },
            {
              "x": 36208,
              "y": 27421,
              "z": 32687
            },
            {
              "x": 36016,
              "y": 28709,
              "z": 32939
            },
            {
              "x": 35896,
              "y": 30181,
              "z": 33169
            },
            {
              "x": 35832,
              "y": 31561,
              "z": 33357
            },
            {
              "x": 35808,
              "y": 32577,
              "z": 33485
            },
            {
              "x": 35800,
              "y": 32977,
              "z": 33533
            },
            {
              "x": 35800,
              "y": 32977,
              "z": 33533
            },
            {
              "x": 35808,
              "y": 32577,
              "z": 33485
            },
            {
              "x": 35832,
              "y": 31561,
              "z": 33357
            },
            {
              "x": 35896,
              "y": 30181,
              "z": 33169
            },
            {
              "x": 36016,
              "y": 28709,
              "z": 32939
            },
            {
              "x": 36208,
              "y": 27421,
              "z": 32687
            },
            {
              "x": 36592,
              "y": 26113,
              "z": 32317
            },
            {
              "x": 37160,
              "y": 24669,
              "z": 31839
            },
            {
              "x": 37720,
              "y": 23501,
              "z": 31425
            },
            {
              "x": 37976,
              "y": 23017,
              "z": 31251
            },
            {
              "x": 37976,
              "y": 23017,
              "z": 31251
            }
          ]
        },
        "translate_type": "FixedVectorTrack",
        "translate": {
          "co": {
            "x": 10.7,
            "y": -3.3000000000000003,
            "z": -6.2
          }
        }
      },
      {
        "name": "right_upper_eyelid_c",
        "scale_type": "FixedVectorTrack",
        "scale": {
          "co": {
            "x": 1.0,
            "y": 1.0,
            "z": 1.0
          }
        },
        "rotate_type": "DynamicRotationTrack",
        "rotate": {
          "co": [
            {
              "x": 27552,
              "y": 23018,
              "z": 34285
            },
            {
              "x": 27808,
              "y": 23502,
              "z": 34111
            },
            {
              "x": 28368,
              "y": 24670,
              "z": 33697
            },
            {
              "x": 28936,
              "y": 26114,
              "z": 33219
            },
            {
              "x": 29320,
              "y": 27422,
              "z": 32849
            },
            {
              "x": 29512,
              "y": 28710,
              "z": 32597
            },
            {
              "x": 29632,
              "y": 30182,
              "z": 32367
            },
            {
              "x": 29696,
              "y": 31562,
              "z": 32179
            },
            {
              "x": 29720,
              "y": 32578,
              "z": 32051
            },
            {
              "x": 29728,
              "y": 32978,
              "z": 32003
            },
            {
              "x": 29728,
              "y": 32978,
              "z": 32003
            },
            {
              "x": 29720,
              "y": 32578,
              "z": 32051
            },
            {
              "x": 29696,
              "y": 31562,
              "z": 32179
            },
            {
              "x": 29632,
              "y": 30182,
              "z": 32367
            },
            {
              "x": 29512,
              "y": 28710,
              "z": 32597
            },
            {
              "x": 29320,
              "y": 27422,
              "z": 32849
            },
            {
              "x": 28936,
              "y": 26114,
              "z": 33219
            },
            {
              "x": 28368,
              "y": 24670,
              "z": 33697
            },
            {
              "x": 27808,
              "y": 23502,
              "z": 34111
            },
            {
              "x": 27552,
              "y": 23018,
              "z": 34285
            },
            {
              "x": 27552,
              "y": 23018,
              "z": 34285
            }
          ]
        },
        "translate_type": "FixedVectorTrack",
        "translate": {
          "co": {
            "x": 10.7,
            "y": 3.3000000000000003,
            "z": -6.2
          }
        }
      },
      {
        "name": "left_upper_eyelid_d",
        "scale_type": "FixedVectorTrack",
        "scale": {
          "co": {
            "x": 1.0,
            "y": 1.0,
            "z": 1.0
          }
        },
        "rotate_type": "DynamicRotationTrack",
        "rotate": {
          "co": [
            {
              "x": 23632,
              "y": 18357,
              "z": 37737
            },
            {
              "x": 23672,
              "y": 18857,
              "z": 37797
            },
            {
              "x": 23776,
              "y": 19969,
              "z": 37935
            },
            {
              "x": 23896,
              "y": 21129,
              "z": 38081
            },
            {
              "x": 23984,
              "y": 21773,
              "z": 38163
            },
            {
              "x": 24008,
              "y": 21897,
              "z": 38257
            },
            {
              "x": 23984,
              "y": 21901,
              "z": 38443
            },
            {
              "x": 23936,
              "y": 21837,
              "z": 38657
            },
            {
              "x": 23888,
              "y": 21757,
              "z": 38831
            },
            {
              "x": 23864,
              "y": 21717,
              "z": 38905
            },
            {
              "x": 23864,
              "y": 21717,
              "z": 38905
            },
            {
              "x": 23888,
              "y": 21757,
              "z": 38831
            },
            {
              "x": 23936,
              "y": 21837,
              "z": 38657
            },
            {
              "x": 23984,
              "y": 21901,
              "z": 38443
            },
            {
              "x": 24008,
              "y": 21897,
              "z": 38257
            },
            {
              "x": 23984,
              "y": 21773,
              "z": 38163
            },
            {
              "x": 23896,
              "y": 21129,
              "z": 38081
            },
            {
              "x": 23776,
              "y": 19969,
              "z": 37935
            },
            {
              "x": 23672,
              "y": 18857,
              "z": 37797
            },
            {
              "x": 23632,
              "y": 18357,
              "z": 37737
            },
            {
              "x": 23632,
              "y": 18357,
              "z": 37737
            }
          ]
        },
        "translate_type": "FixedVectorTrack",
        "translate": {
          "co": {
            "x": -6.2,
            "y": -1.2,
            "z": -16.0
          }
        }
      },
      {
        "name": "right_upper_eyelid_d",
        "scale_type": "FixedVectorTrack",
        "scale": {
          "co": {
            "x": 1.0,
            "y": 1.0,
            "z": 1.0
          }
        },
        "rotate_type": "DynamicRotationTrack",
        "rotate": {
          "co": [
            {
              "x": 41896,
              "y": 18358,
              "z": 27799
            },
            {
              "x": 41856,
              "y": 18858,
              "z": 27739
            },
            {
              "x": 41752,
              "y": 19970,
              "z": 27601
            },
            {
              "x": 41632,
              "y": 21130,
              "z": 27455
            },
            {
              "x": 41544,
              "y": 21774,
              "z": 27373
            },
            {
              "x": 41520,
              "y": 21898,
              "z": 27279
            },
            {
              "x": 41544,
              "y": 21902,
              "z": 27093
            },
            {
              "x": 41592,
              "y": 21838,
              "z": 26879
            },
            {
              "x": 41640,
              "y": 21758,
              "z": 26705
            },
            {
              "x": 41664,
              "y": 21718,
              "z": 26631
            },
            {
              "x": 41664,
              "y": 21718,
              "z": 26631
            },
            {
              "x": 41640,
              "y": 21758,
              "z": 26705
            },
            {
              "x": 41592,
              "y": 21838,
              "z": 26879
            },
            {
              "x": 41544,
              "y": 21902,
              "z": 27093
            },
            {
              "x": 41520,
              "y": 21898,
              "z": 27279
            },
            {
              "x": 41544,
              "y": 21774,
              "z": 27373
            },
            {
              "x": 41632,
              "y": 21130,
              "z": 27455
            },
            {
              "x": 41752,
              "y": 19970,
              "z": 27601
            },
            {
              "x": 41856,
              "y": 18858,
              "z": 27739
            },
            {
              "x": 41896,
              "y": 18358,
              "z": 27799
            },
            {
              "x": 41896,
              "y": 18358,
              "z": 27799
            }
          ]
        },
        "translate_type": "FixedVectorTrack",
        "translate": {
          "co": {
            "x": -6.2,
            "y": 1.2,
            "z": -16.0
          }
        }
      },
      {
        "name": "left_upper_eyelid_e",
        "scale_type": "FixedVectorTrack",
        "scale": {
          "co": {
            "x": 1.0,
            "y": 1.0,
            "z": 1.0
          }
        },
        "rotate_type": "Framed8RotationTrack",
        "rotate": {
          "frames": [
            0,
            0,
            1,
            3,
            4,
            6,
            9,
            12,
            15,
            16,
            18,
            20,
            20
          ],
          "co": [
            {
              "x": 26424,
              "y": 19117,
              "z": 36677
            },
            {
              "x": 26424,
              "y": 19117,
              "z": 36677
            },
            {
              "x": 26528,
              "y": 19381,
              "z": 36713
            },
            {
              "x": 27088,
              "y": 20589,
              "z": 36881
            },
            {
              "x": 27360,
              "y": 20933,
              "z": 36937
            },
            {
              "x": 27976,
              "y": 21069,
              "z": 36987
            },
            {
              "x": 28640,
              "y": 21081,
              "z": 37027
            },
            {
              "x": 28296,
              "y": 21085,
              "z": 37007
            },
            {
              "x": 27360,
              "y": 20933,
              "z": 36937
            },
            {
              "x": 27088,
              "y": 20589,
              "z": 36881
            },
            {
              "x": 26528,
              "y": 19381,
              "z": 36713
            },
            {
              "x": 26424,
              "y": 19117,
              "z": 36677
            },
            {
              "x": 26424,
              "y": 19117,
              "z": 36677
            }
          ]
        },
        "translate_type": "FixedVectorTrack",
        "translate": {
          "co": {
            "x": -8.5,
            "y": -1.5,
            "z": -12.9
          }
        }
      },
      {
        "name": "right_upper_eyelid_e",
        "scale_type": "FixedVectorTrack",
        "scale": {
          "co": {
            "x": 1.0,
            "y": 1.0,
            "z": 1.0
          }
        },
        "rotate_type": "Framed8RotationTrack",
        "rotate": {
          "frames": [
            0,
            0,
            1,
            3,
            4,
            6,
            9,
            12,
            15,
            16,
            18,
            20,
            20
          ],
          "co": [
            {
              "x": 39104,
              "y": 19118,
              "z": 28859
            },
            {
              "x": 39104,
              "y": 19118,
              "z": 28859
            },
            {
              "x": 39000,
              "y": 19382,
              "z": 28823
            },
            {
              "x": 38440,
              "y": 20590,
              "z": 28655
            },
            {
              "x": 38168,
              "y": 20934,
              "z": 28599
            },
            {
              "x": 37552,
              "y": 21070,
              "z": 28549
            },
            {
              "x": 36888,
              "y": 21082,
              "z": 28509
            },
            {
              "x": 37232,
              "y": 21086,
              "z": 28529
            },
            {
              "x": 38168,
              "y": 20934,
              "z": 28599
            },
            {
              "x": 38440,
              "y": 20590,
              "z": 28655
            },
            {
              "x": 39000,
              "y": 19382,
              "z": 28823
            },
            {
              "x": 39104,
              "y": 19118,
              "z": 28859
            },
            {
              "x": 39104,
              "y": 19118,
              "z": 28859
            }
          ]
        },
        "translate_type": "FixedVectorTrack",
        "translate": {
          "co": {
            "x": -8.5,
            "y": 1.5,
            "z": -12.9
          }
        }
      },
      {
        "name": "left_lower_eyelid_a",
        "scale_type": "FixedVectorTrack",
        "scale": {
          "co": {
            "x": 1.0,
            "y": 1.0,
            "z": 1.0
          }
        },
        "rotate_type": "DynamicRotationTrack",
        "rotate": {
          "co": [
            {
              "x": 2091,
              "y": 44813,
              "z": 25616
            },
            {
              "x": 2091,
              "y": 44813,
              "z": 25616
            },
            {
              "x": 2091,
              "y": 44813,
              "z": 25616
            },
            {
              "x": 2091,
              "y": 44813,
              "z": 25616
            },
            {
              "x": 2091,
              "y": 44813,
              "z": 25616
            },
            {
              "x": 3883,
              "y": 44637,
              "z": 25684
            },
            {
              "x": 8179,
              "y": 44225,
              "z": 25858
            },
            {
              "x": 13371,
              "y": 43741,
              "z": 26076
            },
            {
              "x": 17755,
              "y": 43341,
              "z": 26272
            },
            {
              "x": 19603,
              "y": 43177,
              "z": 26358
            },
            {
              "x": 19603,
              "y": 43177,
              "z": 26358
            },
            {
              "x": 17755,
              "y": 43341,
              "z": 26272
            },
            {
              "x": 13371,
              "y": 43741,
              "z": 26076
            },
            {
              "x": 8179,
              "y": 44225,
              "z": 25858
            },
            {
              "x": 3883,
              "y": 44637,
              "z": 25684
            },
            {
              "x": 2091,
              "y": 44813,
              "z": 25616
            },
            {
              "x": 2091,
              "y": 44813,
              "z": 25616
            },
            {
              "x": 2091,
              "y": 44813,
              "z": 25616
            },
            {
              "x": 2091,
              "y": 44813,
              "z": 25616
            },
            {
              "x": 2091,
              "y": 44813,
              "z": 25616
            },
            {
              "x": 2091,
              "y": 44813,
              "z": 25616
            }
          ]
        },
        "translate_type": "FixedVectorTrack",
        "translate": {
          "co": {
            "x": 0.8,
            "y": -2.9000000000000004,
            "z": -6.2
          }
        }
      },
      {
        "name": "right_lower_eyelid_a",
        "scale_type": "FixedVectorTrack",
        "scale": {
          "co": {
            "x": 1.0,
            "y": 1.0,
            "z": 1.0
          }
        },
        "rotate_type": "DynamicRotationTrack",
        "rotate": {
          "co": [
            {
              "x": 63443,
              "y": 44814,
              "z": 39918
            },
            {
              "x": 63443,
              "y": 44814,
              "z": 39918
            },
            {
              "x": 63443,
              "y": 44814,
              "z": 39918
            },
            {
              "x": 63443,
              "y": 44814,
              "z": 39918
            },
            {
              "x": 63443,
              "y": 44814,
              "z": 39918
            },
            {
              "x": 61651,
              "y": 44638,
              "z": 39850
            },
            {
              "x": 57355,
              "y": 44226,
              "z": 39676
            },
            {
              "x": 52163,
              "y": 43742,
              "z": 39458
            },
            {
              "x": 47779,
              "y": 43342,
              "z": 39262
            },
            {
              "x": 45931,
              "y": 43178,
              "z": 39176
            },
            {
              "x": 45931,
              "y": 43178,
              "z": 39176
            },
            {
              "x": 47779,
              "y": 43342,
              "z": 39262
            },
            {
              "x": 52163,
              "y": 43742,
              "z": 39458
            },
            {
              "x": 57355,
              "y": 44226,
              "z": 39676
            },
            {
              "x": 61651,
              "y": 44638,
              "z": 39850
            },
            {
              "x": 63443,
              "y": 44814,
              "z": 39918
            },
            {
              "x": 63443,
              "y": 44814,
              "z": 39918
            },
            {
              "x": 63443,
              "y": 44814,
              "z": 39918
            },
            {
              "x": 63443,
              "y": 44814,
              "z": 39918
            },
            {
              "x": 63443,
              "y": 44814,
              "z": 39918
            },
            {
              "x": 63443,
              "y": 44814,
              "z": 39918
            }
          ]
        },
        "translate_type": "FixedVectorTrack",
        "translate": {
          "co": {
            "x": 0.8,
            "y": 2.9000000000000004,
            "z": -6.2
          }
        }
      },
      {
        "name": "left_lower_eyelid_b",
        "scale_type": "FixedVectorTrack",
        "scale": {
          "co": {
            "x": 1.0,
            "y": 1.0,
            "z": 1.0
          }
        },
        "rotate_type": "Framed8RotationTrack",
        "rotate": {
          "frames": [
            0,
            0,
            4,
            5,
            7,
            9,
            11,
            14,
            20,
            20
          ],
          "co": [
            {
              "x": 5115,
              "y": 29974,
              "z": 25240
            },
            {
              "x": 5115,
              "y": 29974,
              "z": 25240
            },
            {
              "x": 5115,
              "y": 29974,
              "z": 25240
            },
            {
              "x": 5131,
              "y": 30106,
              "z": 25262
            },
            {
              "x": 5211,
              "y": 30806,
              "z": 25380
            },
            {
              "x": 5259,
              "y": 31258,
              "z": 25456
            },
            {
              "x": 5243,
              "y": 31122,
              "z": 25434
            },
            {
              "x": 5131,
              "y": 30106,
              "z": 25262
            },
            {
              "x": 5115,
              "y": 29974,
              "z": 25240
            },
            {
              "x": 5115,
              "y": 29974,
              "z": 25240
            }
          ]
        },
        "translate_type": "FixedVectorTrack",
        "translate": {
          "co": {
            "x": 12.6,
            "y": -3.1,
            "z": -3.6999999999999997
          }
        }
      },
      {
        "name": "right_lower_eyelid_b",
        "scale_type": "FixedVectorTrack",
        "scale": {
          "co": {
            "x": 1.0,
            "y": 1.0,
            "z": 1.0
          }
        },
        "rotate_type": "Framed8RotationTrack",
        "rotate": {
          "frames": [
            0,
            0,
            4,
            5,
            7,
            9,
            11,
            14,
            20,
            20
          ],
          "co": [
            {
              "x": 60419,
              "y": 29973,
              "z": 40294
            },
            {
              "x": 60419,
              "y": 29973,
              "z": 40294
            },
            {
              "x": 60419,
              "y": 29973,
              "z": 40294
            },
            {
              "x": 60403,
              "y": 30105,
              "z": 40272
            },
            {
              "x": 60323,
              "y": 30805,
              "z": 40154
            },
            {
              "x": 60275,
              "y": 31257,
              "z": 40078
            },
            {
              "x": 60291,
              "y": 31121,
              "z": 40100
            },
            {
              "x": 60403,
              "y": 30105,
              "z": 40272
            },
            {
              "x": 60419,
              "y": 29973,
              "z": 40294
            },
            {
              "x": 60419,
              "y": 29973,
              "z": 40294
            }
          ]
        },
        "translate_type": "FixedVectorTrack",
        "translate": {
          "co": {
            "x": 12.6,
            "y": 3.1,
            "z": -3.6999999999999997
          }
        }
      },
      {
        "name": "left_lower_eyelid_c",
        "scale_type": "FixedVectorTrack",
        "scale": {
          "co": {
            "x": 1.0,
            "y": 1.0,
            "z": 1.0
          }
        },
        "rotate_type": "DynamicRotationTrack",
        "rotate": {
          "co": [
            {
              "x": 5915,
              "y": 27203,
              "z": 27702
            },
            {
              "x": 5915,
              "y": 27203,
              "z": 27702
            },
            {
              "x": 5915,
              "y": 27203,
              "z": 27702
            },
            {
              "x": 5915,
              "y": 27203,
              "z": 27702
            },
            {
              "x": 5915,
              "y": 27203,
              "z": 27702
            },
            {
              "x": 4091,
              "y": 27307,
              "z": 27664
            },
            {
              "x": 65227,
              "y": 27562,
              "z": 27560
            },
            {
              "x": 59899,
              "y": 27878,
              "z": 27410
            },
            {
              "x": 55379,
              "y": 28150,
              "z": 27262
            },
            {
              "x": 53467,
              "y": 28266,
              "z": 27194
            },
            {
              "x": 53467,
              "y": 28266,
              "z": 27194
            },
            {
              "x": 55379,
              "y": 28150,
              "z": 27262
            },
            {
              "x": 59899,
              "y": 27878,
              "z": 27410
            },
            {
              "x": 65227,
              "y": 27562,
              "z": 27560
            },
            {
              "x": 4091,
              "y": 27307,
              "z": 27664
            },
            {
              "x": 5915,
              "y": 27203,
              "z": 27702
            },
            {
              "x": 5915,
              "y": 27203,
              "z": 27702
            },
            {
              "x": 5915,
              "y": 27203,
              "z": 27702
            },
            {
              "x": 5915,
              "y": 27203,
              "z": 27702
            },
            {
              "x": 5915,
              "y": 27203,
              "z": 27702
            },
            {
              "x": 5915,
              "y": 27203,
              "z": 27702
            }
          ]
        },
        "translate_type": "FixedVectorTrack",
        "translate": {
          "co": {
            "x": 17.4,
            "y": -7.3,
            "z": 1.3
          }
        }
      },
      {
        "name": "right_lower_eyelid_c",
        "scale_type": "FixedVectorTrack",
        "scale": {
          "co": {
            "x": 1.0,
            "y": 1.0,
            "z": 1.0
          }
        },
        "rotate_type": "DynamicRotationTrack",
        "rotate": {
          "co": [
            {
              "x": 59619,
              "y": 27200,
              "z": 37832
            },
            {
              "x": 59619,
              "y": 27200,
              "z": 37832
            },
            {
              "x": 59619,
              "y": 27200,
              "z": 37832
            },
            {
              "x": 59619,
              "y": 27200,
              "z": 37832
            },
            {
              "x": 59619,
              "y": 27200,
              "z": 37832
            },
            {
              "x": 61443,
              "y": 27304,
              "z": 37870
            },
            {
              "x": 307,
              "y": 27561,
              "z": 37974
            },
            {
              "x": 5635,
              "y": 27877,
              "z": 38124
            },
            {
              "x": 10155,
              "y": 28149,
              "z": 38272
            },
            {
              "x": 12067,
              "y": 28265,
              "z": 38340
            },
            {
              "x": 12067,
              "y": 28265,
              "z": 38340
            },
            {
              "x": 10155,
              "y": 28149,
              "z": 38272
            },
            {
              "x": 5635,
              "y": 27877,
              "z": 38124
            },
            {
              "x": 307,
              "y": 27561,
              "z": 37974
            },
            {
              "x": 61443,
              "y": 27304,
              "z": 37870
            },
            {
              "x": 59619,
              "y": 27200,
              "z": 37832
            },
            {
              "x": 59619,
              "y": 27200,
              "z": 37832
            },
            {
              "x": 59619,
              "y": 27200,
              "z": 37832
            },
            {
              "x": 59619,
              "y": 27200,
              "z": 37832
            },
            {
              "x": 59619,
              "y": 27200,
              "z": 37832
            },
            {
              "x": 59619,
              "y": 27200,
              "z": 37832
            }
          ]
        },
        "translate_type": "FixedVectorTrack",
        "translate": {
          "co": {
            "x": 17.4,
            "y": 7.3,
            "z": 1.3
          }
        }
      },
      {
        "name": "left_upper_eyelid_f",
        "scale_type": "FixedVectorTrack",
        "scale": {
          "co": {
            "x": 1.0,
            "y": 1.0,
            "z": 1.0
          }
        },
        "rotate_type": "Framed8RotationTrack",
        "rotate": {
          "frames": [
            0,
            0,
            5,
            9,
            12,
            14,
            18,
            20,
            20
          ],
          "co": [
            {
              "x": 45571,
              "y": 19538,
              "z": 36437
            },
            {
              "x": 45571,
              "y": 19538,
              "z": 36437
            },
            {
              "x": 45523,
              "y": 20350,
              "z": 36699
            },
            {
              "x": 45475,
              "y": 21018,
              "z": 36913
            },
            {
              "x": 45491,
              "y": 20794,
              "z": 36841
            },
            {
              "x": 45523,
              "y": 20350,
              "z": 36699
            },
            {
              "x": 45571,
              "y": 19606,
              "z": 36459
            },
            {
              "x": 45571,
              "y": 19538,
              "z": 36437
            },
            {
              "x": 45571,
              "y": 19538,
              "z": 36437
            }
          ]
        },
        "translate_type": "FixedVectorTrack",
        "translate": {
          "co": {
            "x": -12.8,
            "y": -9.2,
            "z": 8.4
          }
        }
      },
      {
        "name": "right_upper_eyelid_f",
        "scale_type": "FixedVectorTrack",
        "scale": {
          "co": {
            "x": 1.0,
            "y": 1.0,
            "z": 1.0
          }
        },
        "rotate_type": "Framed8RotationTrack",
        "rotate": {
          "frames": [
            0,
            0,
            5,
            9,
            12,
            14,
            18,
            20,
            20
          ],
          "co": [
            {
              "x": 19963,
              "y": 19537,
              "z": 29099
            },
            {
              "x": 19963,
              "y": 19537,
              "z": 29099
            },
            {
              "x": 20011,
              "y": 20349,
              "z": 28837
            },
            {
              "x": 20059,
              "y": 21017,
              "z": 28623
            },
            {
              "x": 20043,
              "y": 20793,
              "z": 28695
            },
            {
              "x": 20011,
              "y": 20349,
              "z": 28837
            },
            {
              "x": 19963,
              "y": 19605,
              "z": 29077
            },
            {
              "x": 19963,
              "y": 19537,
              "z": 29099
            },
            {
              "x": 19963,
              "y": 19537,
              "z": 29099
            }
          ]
        },
        "translate_type": "FixedVectorTrack",
        "translate": {
          "co": {
            "x": -12.8,
            "y": 9.2,
            "z": 8.4
          }
        }
      },
      {
        "name": "left_upper_eyelid_g",
        "scale_type": "FixedVectorTrack",
        "scale": {
          "co": {
            "x": 1.0,
            "y": 1.0,
            "z": 1.0
          }
        },
        "rotate_type": "DynamicRotationTrack",
        "rotate": {
          "co": [
            {
              "x": 44851,
              "y": 17938,
              "z": 36951
            },
            {
              "x": 44771,
              "y": 18298,
              "z": 37003
            },
            {
              "x": 44587,
              "y": 19130,
              "z": 37123
            },
            {
              "x": 44379,
              "y": 20042,
              "z": 37253
            },
            {
              "x": 44243,
              "y": 20642,
              "z": 37339
            },
            {
              "x": 44179,
              "y": 20906,
              "z": 37377
            },
            {
              "x": 44139,
              "y": 21066,
              "z": 37401
            },
            {
              "x": 44123,
              "y": 21146,
              "z": 37411
            },
            {
              "x": 44115,
              "y": 21178,
              "z": 37417
            },
            {
              "x": 44115,
              "y": 21182,
              "z": 37417
            },
            {
              "x": 44115,
              "y": 21182,
              "z": 37417
            },
            {
              "x": 44115,
              "y": 21178,
              "z": 37417
            },
            {
              "x": 44123,
              "y": 21146,
              "z": 37411
            },
            {
              "x": 44139,
              "y": 21066,
              "z": 37401
            },
            {
              "x": 44179,
              "y": 20906,
              "z": 37377
            },
            {
              "x": 44243,
              "y": 20642,
              "z": 37339
            },
            {
              "x": 44379,
              "y": 20042,
              "z": 37253
            },
            {
              "x": 44587,
              "y": 19130,
              "z": 37123
            },
            {
              "x": 44771,
              "y": 18298,
              "z": 37003
            },
            {
              "x": 44851,
              "y": 17938,
              "z": 36951
            },
            {
              "x": 44851,
              "y": 17938,
              "z": 36951
            }
          ]
        },
        "translate_type": "FixedVectorTrack",
        "translate": {
          "co": {
            "x": -8.200000000000001,
            "y": -10.100000000000001,
            "z": 8.3
          }
        }
      },
      {
        "name": "right_upper_eyelid_g",
        "scale_type": "FixedVectorTrack",
        "scale": {
          "co": {
            "x": 1.0,
            "y": 1.0,
            "z": 1.0
          }
        },
        "rotate_type": "DynamicRotationTrack",
        "rotate": {
          "co": [
            {
              "x": 20683,
              "y": 17937,
              "z": 28585
            },
            {
              "x": 20763,
              "y": 18297,
              "z": 28533
            },
            {
              "x": 20947,
              "y": 19129,
              "z": 28413
            },
            {
              "x": 21155,
              "y": 20041,
              "z": 28283
            },
            {
              "x": 21291,
              "y": 20641,
              "z": 28197
            },
            {
              "x": 21355,
              "y": 20905,
              "z": 28159
            },
            {
              "x": 21395,
              "y": 21065,
              "z": 28135
            },
            {
              "x": 21411,
              "y": 21145,
              "z": 28125
            },
            {
              "x": 21419,
              "y": 21177,
              "z": 28119
            },
            {
              "x": 21419,
              "y": 21181,
              "z": 28119
            },
            {
              "x": 21419,
              "y": 21181,
              "z": 28119
            },
            {
              "x": 21419,
              "y": 21177,
              "z": 28119
            },
            {
              "x": 21411,
              "y": 21145,
              "z": 28125
            },
            {
              "x": 21395,
              "y": 21065,
              "z": 28135
            },
            {
              "x": 21355,
              "y": 20905,
              "z": 28159
            },
            {
              "x": 21291,
              "y": 20641,
              "z": 28197
            },
            {
              "x": 21155,
              "y": 20041,
              "z": 28283
            },
            {
              "x": 20947,
              "y": 19129,
              "z": 28413
            },
            {
              "x": 20763,
              "y": 18297,
              "z": 28533
            },
            {
              "x": 20683,
              "y": 17937,
              "z": 28585
            },
            {
              "x": 20683,
              "y": 17937,
              "z": 28585
            }
          ]
        },
        "translate_type": "FixedVectorTrack",
        "translate": {
          "co": {
            "x": -8.200000000000001,
            "y": 10.100000000000001,
            "z": 8.3
          }
        }
      },
      {
        "name": "left_upper_eyelid_h",
        "scale_type": "FixedVectorTrack",
        "scale": {
          "co": {
            "x": 1.0,
            "y": 1.0,
            "z": 1.0
          }
        },
        "rotate_type": "DynamicRotationTrack",
        "rotate": {
          "co": [
            {
              "x": 7867,
              "y": 17258,
              "z": 41081
            },
            {
              "x": 7755,
              "y": 17522,
              "z": 41087
            },
            {
              "x": 7491,
              "y": 18166,
              "z": 41103
            },
            {
              "x": 7147,
              "y": 18982,
              "z": 41121
            },
            {
              "x": 6819,
              "y": 19758,
              "z": 41137
            },
            {
              "x": 6475,
              "y": 20574,
              "z": 41155
            },
            {
              "x": 6067,
              "y": 21534,
              "z": 41175
            },
            {
              "x": 5675,
              "y": 22450,
              "z": 41191
            },
            {
              "x": 5379,
              "y": 23134,
              "z": 41203
            },
            {
              "x": 5267,
              "y": 23402,
              "z": 41207
            },
            {
              "x": 5267,
              "y": 23402,
              "z": 41207
            },
            {
              "x": 5379,
              "y": 23134,
              "z": 41203
            },
            {
              "x": 5675,
              "y": 22450,
              "z": 41191
            },
            {
              "x": 6067,
              "y": 21534,
              "z": 41175
            },
            {
              "x": 6475,
              "y": 20574,
              "z": 41155
            },
            {
              "x": 6819,
              "y": 19758,
              "z": 41137
            },
            {
              "x": 7147,
              "y": 18982,
              "z": 41121
            },
            {
              "x": 7491,
              "y": 18166,
              "z": 41103
            },
            {
              "x": 7755,
              "y": 17522,
              "z": 41087
            },
            {
              "x": 7867,
              "y": 17258,
              "z": 41081
            },
            {
              "x": 7867,
              "y": 17258,
              "z": 41081
            }
          ]
        },
        "translate_type": "FixedVectorTrack",
        "translate": {
          "co": {
            "x": -9.9,
            "y": -6.7,
            "z": 11.799999999999999
          }
        }
      },
      {
        "name": "right_upper_eyelid_h",
        "scale_type": "FixedVectorTrack",
        "scale": {
          "co": {
            "x": 1.0,
            "y": 1.0,
            "z": 1.0
          }
        },
        "rotate_type": "DynamicRotationTrack",
        "rotate": {
          "co": [
            {
              "x": 57667,
              "y": 17257,
              "z": 24455
            },
            {
              "x": 57779,
              "y": 17521,
              "z": 24449
            },
            {
              "x": 58043,
              "y": 18165,
              "z": 24433
            },
            {
              "x": 58387,
              "y": 18981,
              "z": 24415
            },
            {
              "x": 58715,
              "y": 19757,
              "z": 24399
            },
            {
              "x": 59059,
              "y": 20573,
              "z": 24381
            },
            {
              "x": 59467,
              "y": 21533,
              "z": 24361
            },
            {
              "x": 59859,
              "y": 22449,
              "z": 24345
            },
            {
              "x": 60155,
              "y": 23133,
              "z": 24333
            },
            {
              "x": 60267,
              "y": 23401,
              "z": 24329
            },
            {
              "x": 60267,
              "y": 23401,
              "z": 24329
            },
            {
              "x": 60155,
              "y": 23133,
              "z": 24333
            },
            {
              "x": 59859,
              "y": 22449,
              "z": 24345
            },
            {
              "x": 59467,
              "y": 21533,
              "z": 24361
            },
            {
              "x": 59059,
              "y": 20573,
              "z": 24381
            },
            {
              "x": 58715,
              "y": 19757,
              "z": 24399
            },
            {
              "x": 58387,
              "y": 18981,
              "z": 24415
            },
            {
              "x": 58043,
              "y": 18165,
              "z": 24433
            },
            {
              "x": 57779,
              "y": 17521,
              "z": 24449
            },
            {
              "x": 57667,
              "y": 17257,
              "z": 24455
            },
            {
              "x": 57667,
              "y": 17257,
              "z": 24455
            }
          ]
        },
        "translate_type": "FixedVectorTrack",
        "translate": {
          "co": {
            "x": -9.9,
            "y": 6.7,
            "z": 11.799999999999999
          }
        }
      },
      {
        "name": "left_upper_eyelid_i",
        "scale_type": "FixedVectorTrack",
        "scale": {
          "co": {
            "x": 1.0,
            "y": 1.0,
            "z": 1.0
          }
        },
        "rotate_type": "DynamicRotationTrack",
        "rotate": {
          "co": [
            {
              "x": 34971,
              "y": 9321,
              "z": 44495
            },
            {
              "x": 34691,
              "y": 9789,
              "z": 44449
            },
            {
              "x": 34059,
              "y": 10845,
              "z": 44343
            },
            {
              "x": 33403,
              "y": 11953,
              "z": 44231
            },
            {
              "x": 33035,
              "y": 12581,
              "z": 44165
            },
            {
              "x": 33779,
              "y": 12877,
              "z": 44111
            },
            {
              "x": 35739,
              "y": 13277,
              "z": 44013
            },
            {
              "x": 38123,
              "y": 13669,
              "z": 43905
            },
            {
              "x": 40147,
              "y": 13973,
              "z": 43813
            },
            {
              "x": 40995,
              "y": 14089,
              "z": 43775
            },
            {
              "x": 40995,
              "y": 14089,
              "z": 43775
            },
            {
              "x": 40147,
              "y": 13973,
              "z": 43813
            },
            {
              "x": 38123,
              "y": 13669,
              "z": 43905
            },
            {
              "x": 35739,
              "y": 13277,
              "z": 44013
            },
            {
              "x": 33779,
              "y": 12877,
              "z": 44111
            },
            {
              "x": 33035,
              "y": 12581,
              "z": 44165
            },
            {
              "x": 33403,
              "y": 11953,
              "z": 44231
            },
            {
              "x": 34059,
              "y": 10845,
              "z": 44343
            },
            {
              "x": 34691,
              "y": 9789,
              "z": 44449
            },
            {
              "x": 34971,
              "y": 9321,
              "z": 44495
            },
            {
              "x": 34971,
              "y": 9321,
              "z": 44495
            }
          ]
        },
        "translate_type": "FixedVectorTrack",
        "translate": {
          "co": {
            "x": -6.5,
            "y": 1.0,
            "z": 8.0
          }
        }
      },
      {
        "name": "right_upper_eyelid_i",
        "scale_type": "FixedVectorTrack",
        "scale": {
          "co": {
            "x": 1.0,
            "y": 1.0,
            "z": 1.0
          }
        },
        "rotate_type": "DynamicRotationTrack",
        "rotate": {
          "co": [
            {
              "x": 30563,
              "y": 9322,
              "z": 21041
            },
            {
              "x": 30843,
              "y": 9790,
              "z": 21087
            },
            {
              "x": 31475,
              "y": 10846,
              "z": 21193
            },
            {
              "x": 32131,
              "y": 11954,
              "z": 21305
            },
            {
              "x": 32499,
              "y": 12582,
              "z": 21371
            },
            {
              "x": 31755,
              "y": 12878,
              "z": 21425
            },
            {
              "x": 29795,
              "y": 13278,
              "z": 21523
            },
            {
              "x": 27411,
              "y": 13670,
              "z": 21631
            },
            {
              "x": 25387,
              "y": 13974,
              "z": 21723
            },
            {
              "x": 24539,
              "y": 14090,
              "z": 21761
            },
            {
              "x": 24539,
              "y": 14090,
              "z": 21761
            },
            {
              "x": 25387,
              "y": 13974,
              "z": 21723
            },
            {
              "x": 27411,
              "y": 13670,
              "z": 21631
            },
            {
              "x": 29795,
              "y": 13278,
              "z": 21523
            },
            {
              "x": 31755,
              "y": 12878,
              "z": 21425
            },
            {
              "x": 32499,
              "y": 12582,
              "z": 21371
            },
            {
              "x": 32131,
              "y": 11954,
              "z": 21305
            },
            {
              "x": 31475,
              "y": 10846,
              "z": 21193
            },
            {
              "x": 30843,
              "y": 9790,
              "z": 21087
            },
            {
              "x": 30563,
              "y": 9322,
              "z": 21041
            },
            {
              "x": 30563,
              "y": 9322,
              "z": 21041
            }
          ]
        },
        "translate_type": "FixedVectorTrack",
        "translate": {
          "co": {
            "x": -6.5,
            "y": -1.0,
            "z": 8.0
          }
        }
      },
      {
        "name": "left_upper_eyelid_j",
        "scale_type": "FixedVectorTrack",
        "scale": {
          "co": {
            "x": 1.0,
            "y": 1.0,
            "z": 1.0
          }
        },
        "rotate_type": "Framed8RotationTrack",
        "rotate": {
          "frames": [
            0,
            0,
            1,
            3,
            5,
            7,
            9,
            12,
            15,
            18,
            20,
            20
          ],
          "co": [
            {
              "x": 52915,
              "y": 11805,
              "z": 43353
            },
            {
              "x": 52915,
              "y": 11805,
              "z": 43353
            },
            {
              "x": 52835,
              "y": 11921,
              "z": 43329
            },
            {
              "x": 52443,
              "y": 12529,
              "z": 43187
            },
            {
              "x": 52059,
              "y": 13069,
              "z": 43003
            },
            {
              "x": 51667,
              "y": 13605,
              "z": 42761
            },
            {
              "x": 51467,
              "y": 13865,
              "z": 42635
            },
            {
              "x": 51667,
              "y": 13605,
              "z": 42761
            },
            {
              "x": 52243,
              "y": 12817,
              "z": 43103
            },
            {
              "x": 52835,
              "y": 11921,
              "z": 43329
            },
            {
              "x": 52915,
              "y": 11805,
              "z": 43353
            },
            {
              "x": 52915,
              "y": 11805,
              "z": 43353
            }
          ]
        },
        "translate_type": "FixedVectorTrack",
        "translate": {
          "co": {
            "x": -8.3,
            "y": 0.8999999999999999,
            "z": 4.3999999999999995
          }
        }
      },
      {
        "name": "right_upper_eyelid_j",
        "scale_type": "FixedVectorTrack",
        "scale": {
          "co": {
            "x": 1.0,
            "y": 1.0,
            "z": 1.0
          }
        },
        "rotate_type": "Framed8RotationTrack",
        "rotate": {
          "frames": [
            0,
            0,
            1,
            3,
            5,
            7,
            9,
            12,
            15,
            18,
            20,
            20
          ],
          "co": [
            {
              "x": 12619,
              "y": 11806,
              "z": 22183
            },
            {
              "x": 12619,
              "y": 11806,
              "z": 22183
            },
            {
              "x": 12699,
              "y": 11922,
              "z": 22207
            },
            {
              "x": 13091,
              "y": 12530,
              "z": 22349
            },
            {
              "x": 13475,
              "y": 13070,
              "z": 22533
            },
            {
              "x": 13867,
              "y": 13606,
              "z": 22775
            },
            {
              "x": 14067,
              "y": 13866,
              "z": 22901
            },
            {
              "x": 13867,
              "y": 13606,
              "z": 22775
            },
            {
              "x": 13291,
              "y": 12818,
              "z": 22433
            },
            {
              "x": 12699,
              "y": 11922,
              "z": 22207
            },
            {
              "x": 12619,
              "y": 11806,
              "z": 22183
            },
            {
              "x": 12619,
              "y": 11806,
              "z": 22183
            }
          ]
        },
        "translate_type": "FixedVectorTrack",
        "translate": {
          "co": {
            "x": -8.3,
            "y": -0.8999999999999999,
            "z": 4.3999999999999995
          }
        }
      },
      {
        "name": "left_lower_eyelid_d",
        "scale_type": "FixedVectorTrack",
        "scale": {
          "co": {
            "x": 1.0,
            "y": 1.0,
            "z": 1.0
          }
        },
        "rotate_type": "DynamicRotationTrack",
        "rotate": {
          "co": [
            {
              "x": 22960,
              "y": 48762,
              "z": 46428
            },
            {
              "x": 23008,
              "y": 48750,
              "z": 46426
            },
            {
              "x": 23144,
              "y": 48730,
              "z": 46418
            },
            {
              "x": 23312,
              "y": 48698,
              "z": 46408
            },
            {
              "x": 23488,
              "y": 48666,
              "z": 46400
            },
            {
              "x": 23416,
              "y": 48566,
              "z": 46038
            },
            {
              "x": 22976,
              "y": 48370,
              "z": 45188
            },
            {
              "x": 22376,
              "y": 48154,
              "z": 44170
            },
            {
              "x": 21824,
              "y": 47982,
              "z": 43314
            },
            {
              "x": 21584,
              "y": 47914,
              "z": 42952
            },
            {
              "x": 21584,
              "y": 47914,
              "z": 42952
            },
            {
              "x": 21824,
              "y": 47982,
              "z": 43314
            },
            {
              "x": 22376,
              "y": 48154,
              "z": 44170
            },
            {
              "x": 22976,
              "y": 48370,
              "z": 45188
            },
            {
              "x": 23416,
              "y": 48566,
              "z": 46038
            },
            {
              "x": 23488,
              "y": 48666,
              "z": 46400
            },
            {
              "x": 23312,
              "y": 48698,
              "z": 46408
            },
            {
              "x": 23144,
              "y": 48730,
              "z": 46418
            },
            {
              "x": 23008,
              "y": 48750,
              "z": 46426
            },
            {
              "x": 22960,
              "y": 48762,
              "z": 46428
            },
            {
              "x": 22960,
              "y": 48762,
              "z": 46428
            }
          ]
        },
        "translate_type": "FixedVectorTrack",
        "translate": {
          "co": {
            "x": -15.299999999999999,
            "y": 1.3,
            "z": 9.700000000000001
          }
        }
      },
      {
        "name": "right_lower_eyelid_d",
        "scale_type": "FixedVectorTrack",
        "scale": {
          "co": {
            "x": 1.0,
            "y": 1.0,
            "z": 1.0
          }
        },
        "rotate_type": "DynamicRotationTrack",
        "rotate": {
          "co": [
            {
              "x": 42568,
              "y": 48761,
              "z": 19106
            },
            {
              "x": 42520,
              "y": 48749,
              "z": 19108
            },
            {
              "x": 42384,
              "y": 48729,
              "z": 19116
            },
            {
              "x": 42216,
              "y": 48697,
              "z": 19126
            },
            {
              "x": 42040,
              "y": 48665,
              "z": 19134
            },
            {
              "x": 42112,
              "y": 48565,
              "z": 19496
            },
            {
              "x": 42552,
              "y": 48369,
              "z": 20346
            },
            {
              "x": 43152,
              "y": 48153,
              "z": 21364
            },
            {
              "x": 43704,
              "y": 47981,
              "z": 22220
            },
            {
              "x": 43944,
              "y": 47913,
              "z": 22582
            },
            {
              "x": 43944,
              "y": 47913,
              "z": 22582
            },
            {
              "x": 43704,
              "y": 47981,
              "z": 22220
            },
            {
              "x": 43152,
              "y": 48153,
              "z": 21364
            },
            {
              "x": 42552,
              "y": 48369,
              "z": 20346
            },
            {
              "x": 42112,
              "y": 48565,
              "z": 19496
            },
            {
              "x": 42040,
              "y": 48665,
              "z": 19134
            },
            {
              "x": 42216,
              "y": 48697,
              "z": 19126
            },
            {
              "x": 42384,
              "y": 48729,
              "z": 19116
            },
            {
              "x": 42520,
              "y": 48749,
              "z": 19108
            },
            {
              "x": 42568,
              "y": 48761,
              "z": 19106
            },
            {
              "x": 42568,
              "y": 48761,
              "z": 19106
            }
          ]
        },
        "translate_type": "FixedVectorTrack",
        "translate": {
          "co": {
            "x": -15.299999999999999,
            "y": -1.3,
            "z": 9.700000000000001
          }
        }
      },
      {
        "name": "left_lower_eyelid_e",
        "scale_type": "FixedVectorTrack",
        "scale": {
          "co": {
            "x": 1.0,
            "y": 1.0,
            "z": 1.0
          }
        },
        "rotate_type": "Framed8RotationTrack",
        "rotate": {
          "frames": [
            0,
            0,
            5,
            9,
            11,
            14,
            20,
            20
          ],
          "co": [
            {
              "x": 35096,
              "y": 39354,
              "z": 32242
            },
            {
              "x": 35096,
              "y": 39354,
              "z": 32242
            },
            {
              "x": 35088,
              "y": 39418,
              "z": 32234
            },
            {
              "x": 35072,
              "y": 39962,
              "z": 32174
            },
            {
              "x": 35080,
              "y": 39898,
              "z": 32180
            },
            {
              "x": 35088,
              "y": 39418,
              "z": 32234
            },
            {
              "x": 35096,
              "y": 39354,
              "z": 32242
            },
            {
              "x": 35096,
              "y": 39354,
              "z": 32242
            }
          ]
        },
        "translate_type": "FixedVectorTrack",
        "translate": {
          "co": {
            "x": -9.5,
            "y": -7.3,
            "z": 13.900000000000002
          }
        }
      },
      {
        "name": "right_lower_eyelid_e",
        "scale_type": "FixedVectorTrack",
        "scale": {
          "co": {
            "x": 1.0,
            "y": 1.0,
            "z": 1.0
          }
        },
        "rotate_type": "Framed8RotationTrack",
        "rotate": {
          "frames": [
            0,
            0,
            5,
            9,
            11,
            14,
            20,
            20
          ],
          "co": [
            {
              "x": 30432,
              "y": 39353,
              "z": 33292
            },
            {
              "x": 30432,
              "y": 39353,
              "z": 33292
            },
            {
              "x": 30440,
              "y": 39417,
              "z": 33300
            },
            {
              "x": 30456,
              "y": 39961,
              "z": 33360
            },
            {
              "x": 30448,
              "y": 39897,
              "z": 33354
            },
            {
              "x": 30440,
              "y": 39417,
              "z": 33300
            },
            {
              "x": 30432,
              "y": 39353,
              "z": 33292
            },
            {
              "x": 30432,
              "y": 39353,
              "z": 33292
            }
          ]
        },
        "translate_type": "FixedVectorTrack",
        "translate": {
          "co": {
            "x": -9.5,
            "y": 7.3,
            "z": 13.900000000000002
          }
        }
      },
      {
        "name": "left_lower_eyelid_f",
        "scale_type": "FixedVectorTrack",
        "scale": {
          "co": {
            "x": 1.0,
            "y": 1.0,
            "z": 1.0
          }
        },
        "rotate_type": "DynamicRotationTrack",
        "rotate": {
          "co": [
            {
              "x": 19096,
              "y": 34110,
              "z": 14288
            },
            {
              "x": 19208,
              "y": 34162,
              "z": 14426
            },
            {
              "x": 19480,
              "y": 34290,
              "z": 14766
            },
            {
              "x": 19816,
              "y": 34450,
              "z": 15196
            },
            {
              "x": 20128,
              "y": 34598,
              "z": 15600
            },
            {
              "x": 20440,
              "y": 34750,
              "z": 16024
            },
            {
              "x": 20792,
              "y": 34926,
              "z": 16520
            },
            {
              "x": 21136,
              "y": 35094,
              "z": 16994
            },
            {
              "x": 21400,
              "y": 35222,
              "z": 17352
            },
            {
              "x": 21504,
              "y": 35274,
              "z": 17492
            },
            {
              "x": 21504,
              "y": 35274,
              "z": 17492
            },
            {
              "x": 21400,
              "y": 35222,
              "z": 17352
            },
            {
              "x": 21136,
              "y": 35094,
              "z": 16994
            },
            {
              "x": 20792,
              "y": 34926,
              "z": 16520
            },
            {
              "x": 20440,
              "y": 34750,
              "z": 16024
            },
            {
              "x": 20128,
              "y": 34598,
              "z": 15600
            },
            {
              "x": 19816,
              "y": 34450,
              "z": 15196
            },
            {
              "x": 19480,
              "y": 34290,
              "z": 14766
            },
            {
              "x": 19208,
              "y": 34162,
              "z": 14426
            },
            {
              "x": 19096,
              "y": 34110,
              "z": 14288
            },
            {
              "x": 19096,
              "y": 34110,
              "z": 14288
            }
          ]
        },
        "translate_type": "FixedVectorTrack",
        "translate": {
          "co": {
            "x": 2.7,
            "y": 1.3,
            "z": 5.5
          }
        }
      },
      {
        "name": "right_lower_eyelid_f",
        "scale_type": "FixedVectorTrack",
        "scale": {
          "co": {
            "x": 1.0,
            "y": 1.0,
            "z": 1.0
          }
        },
        "rotate_type": "DynamicRotationTrack",
        "rotate": {
          "co": [
            {
              "x": 46432,
              "y": 34109,
              "z": 51246
            },
            {
              "x": 46320,
              "y": 34161,
              "z": 51108
            },
            {
              "x": 46048,
              "y": 34289,
              "z": 50768
            },
            {
              "x": 45712,
              "y": 34449,
              "z": 50338
            },
            {
              "x": 45400,
              "y": 34597,
              "z": 49934
            },
            {
              "x": 45088,
              "y": 34749,
              "z": 49510
            },
            {
              "x": 44736,
              "y": 34925,
              "z": 49014
            },
            {
              "x": 44392,
              "y": 35093,
              "z": 48540
            },
            {
              "x": 44128,
              "y": 35221,
              "z": 48182
            },
            {
              "x": 44024,
              "y": 35273,
              "z": 48042
            },
            {
              "x": 44024,
              "y": 35273,
              "z": 48042
            },
            {
              "x": 44128,
              "y": 35221,
              "z": 48182
            },
            {
              "x": 44392,
              "y": 35093,
              "z": 48540
            },
            {
              "x": 44736,
              "y": 34925,
              "z": 49014
            },
            {
              "x": 45088,
              "y": 34749,
              "z": 49510
            },
            {
              "x": 45400,
              "y": 34597,
              "z": 49934
            },
            {
              "x": 45712,
              "y": 34449,
              "z": 50338
            },
            {
              "x": 46048,
              "y": 34289,
              "z": 50768
            },
            {
              "x": 46320,
              "y": 34161,
              "z": 51108
            },
            {
              "x": 46432,
              "y": 34109,
              "z": 51246
            },
            {
              "x": 46432,
              "y": 34109,
              "z": 51246
            }
          ]
        },
        "translate_type": "FixedVectorTrack",
        "translate": {
          "co": {
            "x": 2.7,
            "y": -1.3,
            "z": 5.5
          }
        }
      },
      {
        "name": "feeler_b_02",
        "scale_type": "FixedVectorTrack",
        "scale": {
          "co": {
            "x": 1.0,
            "y": 1.0,
            "z": 1.0
          }
        },
        "rotate_type": "FixedRotationTrack",
        "rotate": {
          "co": {
            "x": 3,
            "y": 2,
            "z": 32769
          }
        },
        "translate_type": "FixedVectorTrack",
        "translate": {
          "co": {
            "x": 25.419999999999998,
            "y": -0.0,
            "z": 0.0
          }
        }
      },
      {
        "name": "feeler_b_03",
        "scale_type": "FixedVectorTrack",
        "scale": {
          "co": {
            "x": 1.0,
            "y": 1.0,
            "z": 1.0
          }
        },
        "rotate_type": "FixedRotationTrack",
        "rotate": {
          "co": {
            "x": 3,
            "y": 2,
            "z": 32769
          }
        },
        "translate_type": "FixedVectorTrack",
        "translate": {
          "co": {
            "x": 25.419999999999998,
            "y": 0.0,
            "z": 0.0
          }
        }
      },
      {
        "name": "feeler_b_04",
        "scale_type": "FixedVectorTrack",
        "scale": {
          "co": {
            "x": 1.0,
            "y": 1.0,
            "z": 1.0
          }
        },
        "rotate_type": "FixedRotationTrack",
        "rotate": {
          "co": {
            "x": 3,
            "y": 2,
            "z": 32769
          }
        },
        "translate_type": "FixedVectorTrack",
        "translate": {
          "co": {
            "x": 25.419999999999998,
            "y": 0.0,
            "z": 0.0
          }
        }
      },
      {
        "name": "feeler_b_05",
        "scale_type": "FixedVectorTrack",
        "scale": {
          "co": {
            "x": 1.0,
            "y": 1.0,
            "z": 1.0
          }
        },
        "rotate_type": "FixedRotationTrack",
        "rotate": {
          "co": {
            "x": 3,
            "y": 2,
            "z": 32769
          }
        },
        "translate_type": "FixedVectorTrack",
        "translate": {
          "co": {
            "x": 25.419999999999998,
            "y": 0.0,
            "z": 0.0
          }
        }
      },
      {
        "name": "feeler_b_06",
        "scale_type": "FixedVectorTrack",
        "scale": {
          "co": {
            "x": 1.0,
            "y": 1.0,
            "z": 1.0
          }
        },
        "rotate_type": "FixedRotationTrack",
        "rotate": {
          "co": {
            "x": 3,
            "y": 2,
            "z": 32769
          }
        },
        "translate_type": "FixedVectorTrack",
        "translate": {
          "co": {
            "x": 25.419999999999998,
            "y": 0.0,
            "z": 0.0
          }
        }
      },
      {
        "name": "feeler_b_07",
        "scale_type": "FixedVectorTrack",
        "scale": {
          "co": {
            "x": 1.0,
            "y": 1.0,
            "z": 1.0
          }
        },
        "rotate_type": "FixedRotationTrack",
        "rotate": {
          "co": {
            "x": 3,
            "y": 2,
            "z": 32769
          }
        },
        "translate_type": "FixedVectorTrack",
        "translate": {
          "co": {
            "x": 25.419999999999998,
            "y": 0.0,
            "z": 0.0
          }
        }
      },
      {
        "name": "feeler_b_08",
        "scale_type": "FixedVectorTrack",
        "scale": {
          "co": {
            "x": 1.0,
            "y": 1.0,
            "z": 1.0
          }
        },
        "rotate_type": "FixedRotationTrack",
        "rotate": {
          "co": {
            "x": 3,
            "y": 2,
            "z": 32769
          }
        },
        "translate_type": "FixedVectorTrack",
        "translate": {
          "co": {
            "x": 25.419999999999998,
            "y": 0.0,
            "z": 0.0
          }
        }
      },
      {
        "name": "feeler_b_09",
        "scale_type": "FixedVectorTrack",
        "scale": {
          "co": {
            "x": 1.0,
            "y": 1.0,
            "z": 1.0
          }
        },
        "rotate_type": "FixedRotationTrack",
        "rotate": {
          "co": {
            "x": 3,
            "y": 2,
            "z": 32769
          }
        },
        "translate_type": "FixedVectorTrack",
        "translate": {
          "co": {
            "x": 25.419999999999998,
            "y": 0.0,
            "z": 0.0
          }
        }
      }
    ]
  }
}